metastack_powerset_agent/__init__.py
metastack_powerset_agent/agent.py
metastack_powerset_agent/cli.py
payloaddiscovery_powerset_agent/__init__.py
payloaddiscovery_powerset_agent/agent.py
payloaddiscovery_powerset_agent/cli.py
powerset_agents_core/__init__.py
powerset_agents_core/config.py
powerset_agents_core/factory.py
powerset_agents_core-0.1.0.dist-info/METADATA
powerset_agents_core-0.1.0.dist-info/WHEEL
powerset_agents_core-0.1.0.dist-info/top_level.txt
powerset_agents_core-0.1.0.dist-info/RECORD
