Metadata-Version: 2.4
Name: powerset-agents-core
Version: 0.1.0
Summary: Core factory for creating self-improving BaseHeavenAgent instances that learn libraries through PayloadDiscovery
Author-email: HEAVEN Framework <noreply@heaven.framework>
License: MIT
Project-URL: Homepage, https://github.com/sancovp/powerset-agents-core
Project-URL: Repository, https://github.com/sancovp/powerset-agents-core.git
Project-URL: Issues, https://github.com/sancovp/powerset-agents-core/issues
Keywords: agents,heaven,payload-discovery,starlog,self-improvement
Classifier: Development Status :: 3 - Alpha
Classifier: Intended Audience :: Developers
Classifier: License :: OSI Approved :: MIT License
Classifier: Programming Language :: Python :: 3
Classifier: Programming Language :: Python :: 3.9
Classifier: Programming Language :: Python :: 3.10
Classifier: Programming Language :: Python :: 3.11
Classifier: Programming Language :: Python :: 3.12
Classifier: Topic :: Software Development :: Libraries :: Python Modules
Classifier: Topic :: Scientific/Engineering :: Artificial Intelligence
Requires-Python: >=3.9
Requires-Dist: heaven-framework
Requires-Dist: starlog-mcp
Requires-Dist: payload-discovery
Requires-Dist: pydantic>=2.0.0
Requires-Dist: pydantic-settings>=2.0.0
Provides-Extra: dev
Requires-Dist: pytest>=7.0; extra == "dev"
Requires-Dist: pytest-asyncio>=0.21.0; extra == "dev"
Requires-Dist: black>=23.0.0; extra == "dev"
Requires-Dist: ruff>=0.1.0; extra == "dev"
Requires-Dist: mypy>=1.5.0; extra == "dev"
